pytest_anything.py
pytest_anything-0.1.4.dist-info/LICENSE.txt
pytest_anything-0.1.4.dist-info/METADATA
pytest_anything-0.1.4.dist-info/WHEEL
pytest_anything-0.1.4.dist-info/entry_points.txt
pytest_anything-0.1.4.dist-info/top_level.txt
pytest_anything-0.1.4.dist-info/RECORD
