Metadata-Version: 2.1
Name: pytest-anything
Version: 0.1.4
Summary: Pytest fixtures to assert anything and something
Home-page: https://gitlab.com/diefans/pytest-anything
Author: Oliver Berger
Author-email: diefans@gmail.com
Classifier: Programming Language :: Python :: 3
Classifier: License :: OSI Approved :: The Unlicense (Unlicense)
Classifier: Framework :: Pytest
Requires-Python: >=3.7,<4.0
License-File: LICENSE.txt
Requires-Dist: pytest
Provides-Extra: tests
Requires-Dist: pytest <5.0,>=4.6 ; extra == 'tests'
Requires-Dist: pytest-mock ; extra == 'tests'
Requires-Dist: pdbpp ; extra == 'tests'
